questions_three_selenium/__init__.py
questions_three_selenium/module_cfg.yml
questions_three_selenium/browser/__init__.py
questions_three_selenium/browser/browser.py
questions_three_selenium/browser/browserstack.py
questions_three_selenium/browser/kwargs2selector.py
questions_three_selenium/browser/launch_browser.py
questions_three_selenium/browser/require_browserstack_tunnel.py
questions_three_selenium/browser/selenium_grid.py
questions_three_selenium/browser_stack_tunnel/__init__.py
questions_three_selenium/browser_stack_tunnel/browser_stack_tunnel.py
questions_three_selenium/dom_dumper/__init__.py
questions_three_selenium/dom_dumper/dump_dom.js
questions_three_selenium/dom_dumper/dump_dom.py
questions_three_selenium/exceptions/__init__.py
questions_three_selenium-3.12.0.0.dist-info/METADATA
questions_three_selenium-3.12.0.0.dist-info/WHEEL
questions_three_selenium-3.12.0.0.dist-info/top_level.txt
questions_three_selenium-3.12.0.0.dist-info/RECORD
